jjgo/config.py
jjgo-0.0.1.dist-info/WHEEL
jjgo-0.0.1.dist-info/METADATA
jjgo-0.0.1.dist-info/RECORD
