Metadata-Version: 2.1
Name: jjgo
Version: 0.0.1
Summary: 
Author: Jose Javier
Author-email: 3844846+JJGO@users.noreply.github.com
Requires-Python: >=3.9,<4.0
Classifier: Programming Language :: Python :: 3
Classifier: Programming Language :: Python :: 3.9
Classifier: Programming Language :: Python :: 3.10
Classifier: Programming Language :: Python :: 3.11
Requires-Dist: pyyaml (>=6.0,<7.0)
